taskanalytics_data_wrapper/__init__.py
taskanalytics_data_wrapper/taskanalytics_api.py
taskanalytics_data_wrapper-0.3.0.dist-info/licenses/LICENSE
taskanalytics_data_wrapper-0.3.0.dist-info/METADATA
taskanalytics_data_wrapper-0.3.0.dist-info/WHEEL
taskanalytics_data_wrapper-0.3.0.dist-info/top_level.txt
taskanalytics_data_wrapper-0.3.0.dist-info/RECORD
