Metadata-Version: 2.4
Name: taskanalytics-data-wrapper
Version: 0.3.0
Summary: a wrapper for using Task Analytics APIs and downloading survey responses
Author-email: Tobias McVey <tobias.mcvey@nav.no>
License: MIT License
Project-URL: Homepage, https://github.com/navikt/taskanalytics-data-wrapper
Keywords: Task Analytics,Top Tasks
Requires-Python: >=3.10
License-File: LICENSE
Requires-Dist: requests>=2.32.3
Requires-Dist: tqdm>=4.67.1
Dynamic: license-file
